Metadata-Version: 2.1
Name: asx
Version: 1.5.0
Summary: Python library to access the ASX API: https://www.asx.com.au/asx/1/share
Home-page: https://github.com/leighcurran/ASX
Author: Leigh Curran
Author-email: ASXPy@outlook.com
License: MIT
Keywords: ASX,API
Platform: UNKNOWN
Classifier: Development Status :: 3 - Alpha
Classifier: Intended Audience :: Developers
Classifier: Topic :: Software Development :: Build Tools
Classifier: License :: OSI Approved :: MIT License
Classifier: Programming Language :: Python :: 3.5
Classifier: Programming Language :: Python :: 3.6
Classifier: Programming Language :: Python :: 3.7
Classifier: Programming Language :: Python :: 3.8
Classifier: Programming Language :: Python :: 3.9
License-File: LICENSE.txt
